scrapingrps/__init__.py
scrapingrps/scrapingrps.py
scrapingrps-0.8.dist-info/METADATA
scrapingrps-0.8.dist-info/WHEEL
scrapingrps-0.8.dist-info/top_level.txt
scrapingrps-0.8.dist-info/RECORD
