Metadata-Version: 2.1
Name: scrapingrps
Version: 0.8
Summary: Scraping interno
Home-page: https://github.com/rafaelpsampaio/scrapingrps
Author: Rafael Perroud Sampaio
Author-email: rafapsampaio@gmail.com
Classifier: Programming Language :: Python :: 3
Classifier: License :: OSI Approved :: MIT License
Classifier: Operating System :: OS Independent
Requires-Python: >=3.6
Requires-Dist: selenium
Requires-Dist: pandas
Requires-Dist: webdriver-manager
Requires-Dist: sqlalchemy
